document_image_utils/__init__.py
document_image_utils/box.py
document_image_utils/image.py
document_image_utils/leptonica_lib/adjust_rotation
document_image_utils/leptonica_lib/adjust_rotation.c
document_image_utils/leptonica_lib/segment_doc
document_image_utils/leptonica_lib/segment_document.c
document_image_utils/leptonica_lib/tempCodeRunnerFile.sh
document_image_utils/scripts/auto_crop/__init__.py
document_image_utils/scripts/binarize/__init__.py
document_image_utils/scripts/rotate_document/__init__.py
document_image_utils/scripts/split_columns/__init__.py
document_image_utils-0.1.25.5.dist-info/METADATA
document_image_utils-0.1.25.5.dist-info/WHEEL
document_image_utils-0.1.25.5.dist-info/entry_points.txt
document_image_utils-0.1.25.5.dist-info/RECORD
