Metadata-Version: 2.1
Name: document_image_utils
Version: 0.1.25.5
Summary: Toolkit for document image processing
Author: Gonçalo Afonso
Author-email: brazafonso2001@gmail.com
Requires-Python: >=3.10.11,<4.0.0
Classifier: Programming Language :: Python :: 3
Classifier: Programming Language :: Python :: 3.11
Classifier: Programming Language :: Python :: 3.12
Requires-Dist: matplotlib
Requires-Dist: opencv-python (>=4.9.0.80,<5.0.0.0)
Requires-Dist: scipy
Requires-Dist: whittaker_eilers
